README.rst
setup.py
bob/__init__.py
bob.paper.eusipco2018.egg-info/PKG-INFO
bob.paper.eusipco2018.egg-info/SOURCES.txt
bob.paper.eusipco2018.egg-info/dependency_links.txt
bob.paper.eusipco2018.egg-info/entry_points.txt
bob.paper.eusipco2018.egg-info/requires.txt
bob.paper.eusipco2018.egg-info/top_level.txt
bob/paper/__init__.py
bob/paper/eusipco2018/__init__.py
bob/paper/eusipco2018/database/SAVIdatabase.py
bob/paper/eusipco2018/database/__init__.py
bob/paper/eusipco2018/pipelines/__init__.py
bob/paper/eusipco2018/pipelines/evaluation_pipeline.py
bob/paper/eusipco2018/pipelines/generic_config.py
bob/paper/eusipco2018/pipelines/grid_config_idiap.py
bob/paper/eusipco2018/pipelines/grid_config_local.py
bob/paper/eusipco2018/pipelines/step1_process_audio.py
bob/paper/eusipco2018/pipelines/step2_process_video.py
bob/paper/eusipco2018/pipelines/step3_extract_features.py
bob/paper/eusipco2018/pipelines/step4_apply_pca.py
bob/paper/eusipco2018/pipelines/step4_onegmm_classifier.py
bob/paper/eusipco2018/pipelines/step5_evaluate_with_tf.py
bob/paper/eusipco2018/pipelines/step5_svm_classifier.py
bob/paper/eusipco2018/pipelines/tfrecord_config.py
bob/paper/eusipco2018/script/__init__.py
bob/paper/eusipco2018/script/train_with_tensorflow.py
bob/paper/eusipco2018/utils/__init__.py
bob/paper/eusipco2018/utils/image_operations.py